pymusical/__init__.py
pymusical/converter.py
pymusical-0.2.4.dist-info/LICENCE
pymusical-0.2.4.dist-info/METADATA
pymusical-0.2.4.dist-info/WHEEL
pymusical-0.2.4.dist-info/top_level.txt
pymusical-0.2.4.dist-info/RECORD
