Metadata-Version: 2.1
Name: pymusical
Version: 0.2.4
Summary: A small converter for musical and physical values
Home-page: https://github.com/jgueting/pymusical
Author: Johannes Güting
Author-email: jgueting@googlemail.com
License: UNKNOWN
Platform: UNKNOWN
Classifier: Programming Language :: Python :: 3
Classifier: License :: OSI Approved :: MIT License
Classifier: Operating System :: OS Independent
Requires-Python: >=3.6
Requires-Dist: pyparsing
